LICENSE
MANIFEST.in
README.rst
requirements.txt
setup.cfg
setup.py
ckanext/__init__.py
ckanext/gt_theme/__init__.py
ckanext/gt_theme/plugin.py
ckanext/gt_theme/public/css/gt.css
ckanext/gt_theme/public/img/background.png
ckanext/gt_theme/public/img/calculator.png
ckanext/gt_theme/public/img/db.png
ckanext/gt_theme/public/img/docs.png
ckanext/gt_theme/public/img/edit.png
ckanext/gt_theme/public/img/gauge.png
ckanext/gt_theme/public/img/gobierno.png
ckanext/gt_theme/public/img/minfin.png
ckanext/gt_theme/public/img/network.png
ckanext/gt_theme/public/img/person.png
ckanext/gt_theme/public/img/person_chart.png
ckanext/gt_theme/public/img/red.jpg
ckanext/gt_theme/public/img/red.png
ckanext/gt_theme/templates/base.html
ckanext/gt_theme/templates/footer.html
ckanext/gt_theme/templates/header.html
ckanext/gt_theme/templates/page.html
ckanext/gt_theme/templates/home/index.html
ckanext/gt_theme/templates/home/layout1.html
ckanext/gt_theme/templates/home/snippets/promoted.html
ckanext/gt_theme/tests/__init__.py
ckanext/gt_theme/tests/test_plugin.py
ckanext_gt_theme.egg-info/PKG-INFO
ckanext_gt_theme.egg-info/SOURCES.txt
ckanext_gt_theme.egg-info/dependency_links.txt
ckanext_gt_theme.egg-info/entry_points.txt
ckanext_gt_theme.egg-info/namespace_packages.txt
ckanext_gt_theme.egg-info/top_level.txt