Metadata-Version: 1.1
Name: ckanext-gt-theme
Version: 0.0.3
Summary: Minfin theme extension for CKAN
Home-page: https://github.com//ckanext-gt_theme
Author: Javier Pérez, Donald Velásquez
Author-email: javier.alejandro92@gmail.com, davelagui@gmail.com, info@redciudadana.org
License: AGPL
Keywords: CKAN,Guatemala,Finanzas,Gobierno
Platform: UNKNOWN
Classifier: Development Status :: 4 - Beta
Classifier: License :: OSI Approved :: GNU Affero General Public License v3 or later (AGPLv3+)
Classifier: Programming Language :: Python :: 2.7
